snakecharmerpackage/__init__.py
snakecharmerpackage/__main__.py
snakecharmerpackage/random_snake.py
snakecharmerpackage/settings.py
snakecharmerpackage/tests.py
snakecharmers-0.1.1.dist-info/licenses/LICENSE
snakecharmers-0.1.1.dist-info/METADATA
snakecharmers-0.1.1.dist-info/WHEEL
snakecharmers-0.1.1.dist-info/entry_points.txt
snakecharmers-0.1.1.dist-info/top_level.txt
snakecharmers-0.1.1.dist-info/RECORD
