Metadata-Version: 2.4
Name: snakecharmers
Version: 0.1.1
Summary: A tiny, non-serious package
Author-email: Ray Ochotta <amo9758@nyu.edu>, Eli Sun <ys3967@nyu.edu>, Kurt Lukowitsch <kl3641@nyu.edu>, Samantha Lin <sal9791@nyu.edu>
License:                     GNU GENERAL PUBLIC LICENSE
Project-URL: Homepage, https://github.com/software-students-spring2025/3-python-package-snake-charmers-on-a-plane/
Project-URL: Repository, https://github.com/software-students-spring2025/3-python-package-snake-charmers-on-a-plane.git
Project-URL: Bug Tracker, https://github.com/software-students-spring2025/3-python-package-snake-charmers-on-a-plane/issues
Keywords: python,package,build,tutorial
Classifier: Programming Language :: Python :: 3
Classifier: Intended Audience :: Education
Classifier: License :: OSI Approved :: GNU General Public License v3 (GPLv3)
Classifier: Operating System :: OS Independent
Requires-Python: >=3.7
License-File: LICENSE
Provides-Extra: dev
Requires-Dist: pytest; extra == "dev"
Dynamic: license-file
